controlman/__init__.py
controlman/__main__.py
controlman/_file_util.py
controlman/cache_manager.py
controlman/center_manager.py
controlman/changelog_manager.py
controlman/const.py
controlman/data_helper.py
controlman/data_loader.py
controlman/data_validator.py
controlman/datatype.py
controlman/date.py
controlman/hook_manager.py
controlman/reporter.py
controlman/_data/language_code_iso_639_2.json
controlman/_data/schema/cache.yaml
controlman/_data/schema/changelog.yaml
controlman/_data/schema/contributors.yaml
controlman/_data/schema/local.yaml
controlman/_data/schema/main.yaml
controlman/_data/schema/variables.yaml
controlman/_data/schema/def/bash_task.yaml
controlman/_data/schema/def/bash_task_prefix_suffix.yaml
controlman/_data/schema/def/bash_task_setting.yaml
controlman/_data/schema/def/bash_task_setting_details.yaml
controlman/_data/schema/def/branch.yaml
controlman/_data/schema/def/cache-retention-hours.yaml
controlman/_data/schema/def/codeowner.yaml
controlman/_data/schema/def/commit-auto.yaml
controlman/_data/schema/def/commit.yaml
controlman/_data/schema/def/conda-meta-array.yaml
controlman/_data/schema/def/conda-meta-bool.yaml
controlman/_data/schema/def/conda-meta-object.yaml
controlman/_data/schema/def/conda-meta-value.yaml
controlman/_data/schema/def/conditional-task.yaml
controlman/_data/schema/def/dep.yaml
controlman/_data/schema/def/dep_apt_env.yaml
controlman/_data/schema/def/dep_conda_env.yaml
controlman/_data/schema/def/dep_pip_env.yaml
controlman/_data/schema/def/dependency.yaml
controlman/_data/schema/def/devcontainer.yaml
controlman/_data/schema/def/dynamic-data.yaml
controlman/_data/schema/def/dynamic-file-path.yaml
controlman/_data/schema/def/dynamic-file-setting-json.yaml
controlman/_data/schema/def/dynamic-file-setting-md.yaml
controlman/_data/schema/def/dynamic-file-setting-yaml.yaml
controlman/_data/schema/def/dynamic-file.yaml
controlman/_data/schema/def/entity-def.yaml
controlman/_data/schema/def/entity-ids.yaml
controlman-0.1.0.dist-info/METADATA
controlman-0.1.0.dist-info/WHEEL
controlman-0.1.0.dist-info/top_level.txt
controlman-0.1.0.dist-info/RECORD
