Metadata-Version: 2.2
Name: ControlMan
Version: 0.1.0
Requires-Python: >=3.10
Requires-Dist: packaging<24,>=23.2
Requires-Dist: trove-classifiers>=2024.9.12
Requires-Dist: jsonschema<5,>=4.23
Requires-Dist: referencing>=0.35.1
Requires-Dist: jsonpath-ng<2,>=1.6.1
Requires-Dist: ruamel.yaml<0.19,>=0.18.6
Requires-Dist: Jinja2<4,>=3
Requires-Dist: PyLinks<0.2,>=0.1
Requires-Dist: LoggerMan<0.2,>=0.1
Requires-Dist: PySerials<0.2,>=0.1
Requires-Dist: GitTidy<0.2,>=0.1
Requires-Dist: PkgData<0.2,>=0.1
Requires-Dist: PyShellMan<0.2,>=0.1
Requires-Dist: PySyntax<0.2,>=0.1
Requires-Dist: ExceptionMan<0.2,>=0.1
Requires-Dist: MDit<0.2,>=0.1
Requires-Dist: JSONSchemata<0.2,>=0.1
Requires-Dist: VersionMan<0.2,>=0.1
Requires-Dist: HTMP<0.2,>=0.1
Requires-Dist: LicenseMan<0.2,>=0.1
